innov8r/__init__.py
innov8r/__main__.py
innov8r/assistance.py
innov8r/ast_utils.py
innov8r/backend.py
innov8r/base_file_browser.py
innov8r/codeview.py
innov8r/common.py
innov8r/config.py
innov8r/config_ui.py
innov8r/editor_helpers.py
innov8r/editors.py
innov8r/export.py
innov8r/first_run.py
innov8r/flask_app.py
innov8r/gridtable.py
innov8r/jedi_utils.py
innov8r/languages.py
innov8r/login_validator.py
innov8r/memory.py
innov8r/misc_utils.py
innov8r/roughparse.py
innov8r/rst_utils.py
innov8r/running.py
innov8r/shell.py
innov8r/terminal.py
innov8r/tktextext.py
innov8r/token_utils.py
innov8r/udisks.py
innov8r/ui_utils.py
innov8r/workbench.py
innov8r/workdlg.py
innov8r/plugins/__init__.py
innov8r/plugins/about.py
innov8r/plugins/assistant_config_page.py
innov8r/plugins/ast_view.py
innov8r/plugins/autocomplete.py
innov8r/plugins/backend_config_page.py
innov8r/plugins/base_syntax_themes.py
innov8r/plugins/base_ui_themes.py
innov8r/plugins/birdseye_frontend.py
innov8r/plugins/calltip.py
innov8r/plugins/cells.py
innov8r/plugins/clean_ui_themes.py
innov8r/plugins/coloring.py
innov8r/plugins/commenting_indenting.py
innov8r/plugins/common_editing_commands.py
innov8r/plugins/debugger.py
innov8r/plugins/dock_user_windows_frontend.py
innov8r/plugins/editor_config_page.py
innov8r/plugins/event_logging.py
innov8r/plugins/event_view.py
innov8r/plugins/files.py
innov8r/plugins/find_replace.py
innov8r/plugins/general_config_page.py
innov8r/plugins/goto_definition.py
innov8r/plugins/heap.py
innov8r/plugins/highlight_names.py
innov8r/plugins/locals_marker.py
innov8r/plugins/misc_analyzers.py
innov8r/plugins/notes.py
innov8r/plugins/object_inspector.py
innov8r/plugins/outline.py
innov8r/plugins/paren_matcher.py
innov8r/plugins/pgzero_frontend.py
innov8r/plugins/pip_gui.py
innov8r/plugins/pythontutor.py
innov8r/plugins/remove_old_data_dir.py
innov8r/plugins/replayer.py
innov8r/plugins/run_debug_config_page.py
innov8r/plugins/shell_config_page.py
innov8r/plugins/shell_macro.py
innov8r-5.0.3.dist-info/METADATA
innov8r-5.0.3.dist-info/WHEEL
innov8r-5.0.3.dist-info/top_level.txt
innov8r-5.0.3.dist-info/RECORD
